<includes>
	<include name="HomeAccessoriesMenu">
		
		<control type="group" id="1400">
			<include>home-start-column</include>
			<include>zoomout</include>
			<include>home-submenu</include>
			<include>fadeinout</include>
			<posx>332</posx>
			<posy>55</posy>
			<onup>9000</onup>
		
			<visible allowhiddenfocus="true">ControlGroup(9000).HasFocus(4) | ControlGroup(1400).HasFocus(0)</visible>	
			
			<control type="buttonscroller" id="800">
				<visible allowhiddenfocus="true">Control.HasFocus(800)</visible>
				<posx>0</posx>
				<posy>0</posy>
				<width>420</width>
				<height>37</height>
				<buttongap>0</buttongap>
				<numbuttons>7</numbuttons>
				<orientation>vertical</orientation>
				<align>left</align>
				<aligny>center</aligny>
				<movement>0</movement>
				<defaultbutton>2</defaultbutton>
				<wraparound>yes</wraparound>
				<smoothscrolling>yes</smoothscrolling>
				<alpha>70</alpha>
				<font>homemenu</font>
				<onleft>9000</onleft>
				<onright>9000</onright>
				<ondown>700</ondown>
				<onup>700</onup>
				<texturefocus>-</texturefocus>
				<texturenofocus>-</texturenofocus>
				<textoffsetx>0</textoffsetx>
				<textcolor>FF97d9ff</textcolor>
				<focusedcolor>ffffffff</focusedcolor>
				<include>select</include>
	
				<buttons>

					<button id="1">
						<label>1036</label>
						<onclick>ActivateWindow(Favourites)</onclick>
					</button>
					
					<button id="2">
						<label>10001</label>
						<onclick>ActivateWindow(MyPrograms)</onclick>
					</button>
					
					<button id="3">
						<label>10020</label>
						<onclick>ActivateWindow(MyScripts)</onclick>
					</button>
				
					<button id="4">
						<label>10508</label>
						<onclick>ActivateWindow(MyWeather)</onclick>
					</button>
					
					<button id="5">
						<label>7</label>
						<onclick>ActivateWindow(Filemanager)</onclick>
					</button>

					<button id="6">
						<label>130</label>
						<onclick>ActivateWindow(SystemInfo)</onclick>
					</button>
					
					<button id="7">
						<label>31905</label>
						<onclick>XBMC.RunScript(Q:\scripts\T3CH Upgrader\default.py)</onclick>
					</button>
						
				</buttons>
			</control>
		</control>
		
	</include>
</includes>
